{
  "db_name": "PostgreSQL",
  "query": "\n                    SELECT organization_invite_template FROM deployment_email_templates WHERE deployment_id = $1\n                    ",
  "describe": {
    "columns": [
      {
        "ordinal": 0,
        "name": "organization_invite_template",
        "type_info": "Jsonb"
      }
    ],
    "parameters": {
      "Left": [
        "Int8"
      ]
    },
    "nullable": [
      false
    ]
  },
  "hash": "7c510d7cc26f4a0a223d2473c2f6daf73867d7fa816f991528f086cc0c22d6ca"
}
